{
    "code": "N01",
    "message": "数据获取成功",
    "contents": [
        {
            "month": "1",
            "samplePassRateTarget": "0.75",
            "samplePassRate": "0.81"

        },
        {
            "month": "2",
            "samplePassRateTarget": "0.75",
            "samplePassRate": "0.82"
        },
        {
            "month": "3",
            "samplePassRateTarget": "0.8",
            "samplePassRate": "0.8"
        },
        {
            "month": "4",
            "samplePassRateTarget": "0.8",
            "samplePassRate": "0.81"
        },
        {
            "month": "5",
            "samplePassRateTarget": "0.85",
            "samplePassRate": "0.75"
        },
        {
            "month": "6",
            "samplePassRateTarget": "0.85",
            "samplePassRate": "0.78"
        },
        {
            "month": "7",
            "samplePassRateTarget": "0.8",
            "samplePassRate": "0.8"
        },
        {
            "month": "8",
            "samplePassRateTarget": "0.74",
            "samplePassRate": "0.76"
        },
        {
            "month": "9",
            "samplePassRateTarget": "0.78",
            "samplePassRate": "0.75"
        },
        {
            "month": "10",
            "samplePassRateTarget": "0.83",
            "samplePassRate": "0.8"
        },
        {
            "month": "11",
            "samplePassRateTarget": "0.83",
            "samplePassRate": "0.82"
        },
        {
            "month": "12",
            "samplePassRateTarget": "0.65",
            "samplePassRate": "0.7"
        }
    ]
}